edgegap_time/__init__.py
edgegap_time/_duration.py
edgegap_time/_pydantic.py
edgegap_time-1.3.12.dist-info/METADATA
edgegap_time-1.3.12.dist-info/WHEEL
edgegap_time-1.3.12.dist-info/RECORD
