Metadata-Version: 2.1
Name: edgegap-time
Version: 1.3.12
Summary: The Edgegap Time library. Handle generic time operations. Add custom type to manipulate time.
Author: Maxime Boisvert
Author-email: maxime.boisvert@edgegap.com
Requires-Python: >=3.10,<4.0
Classifier: Programming Language :: Python :: 3
Classifier: Programming Language :: Python :: 3.10
Classifier: Programming Language :: Python :: 3.11
Classifier: Programming Language :: Python :: 3.12
Requires-Dist: pydantic (>=2.7.1,<3.0.0)
Requires-Dist: pytimeparse (>=1.1.8,<2.0.0)
